<?xml version="1.0" encoding="UTF-8" ?>
<!DOCTYPE mapper PUBLIC "-//mybatis.org//DTD Mapper 3.0//EN" "http://mybatis.org/dtd/mybatis-3-mapper.dtd" >
<mapper namespace="com.xoa.dao.attendance.AttendLeaveParamMapper" >
  <resultMap id="BaseResultMap" type="com.xoa.model.attendance.AttendLeaveParam" >
    <!--
      WARNING - @mbggenerated
      This element is automatically generated by MyBatis Generator, do not modify.
    -->
    <id column="ALPID" property="alpid" jdbcType="INTEGER" />
    <result column="WORKING_YEARS" property="workingYears" jdbcType="INTEGER" />
    <result column="LEAVE_DAY" property="leaveDay" jdbcType="INTEGER" />
  </resultMap>
  <sql id="Base_Column_List" >
    <!--
      WARNING - @mbggenerated
      This element is automatically generated by MyBatis Generator, do not modify.
    -->
    ALPID, WORKING_YEARS, LEAVE_DAY
  </sql>
  <select id="selectByPrimaryKey" resultMap="BaseResultMap" parameterType="java.lang.Integer" >
    <!--
      WARNING - @mbggenerated
      This element is automatically generated by MyBatis Generator, do not modify.
    -->
    select 
    <include refid="Base_Column_List" />
    from attend_leave_param
    where ALPID = #{alpid,jdbcType=INTEGER}
  </select>
  <delete id="deleteByPrimaryKey" parameterType="java.lang.Integer" >
    <!--
      WARNING - @mbggenerated
      This element is automatically generated by MyBatis Generator, do not modify.
    -->
    delete from attend_leave_param
    where ALPID = #{alpid,jdbcType=INTEGER}
  </delete>
  <insert id="insert" parameterType="com.xoa.model.attendance.AttendLeaveParam" >
    <!--
      WARNING - @mbggenerated
      This element is automatically generated by MyBatis Generator, do not modify.
    -->
    insert into attend_leave_param (ALPID, WORKING_YEARS, LEAVE_DAY
      )
    values (#{alpid,jdbcType=INTEGER}, #{workingYears,jdbcType=INTEGER}, #{leaveDay,jdbcType=INTEGER}
      )
  </insert>
  <insert id="insertSelective" parameterType="com.xoa.model.attendance.AttendLeaveParam" >
    <!--
      WARNING - @mbggenerated
      This element is automatically generated by MyBatis Generator, do not modify.
    -->
    insert into attend_leave_param
    <trim prefix="(" suffix=")" suffixOverrides="," >
      <if test="alpid != null" >
        ALPID,
      </if>
      <if test="workingYears != null" >
        WORKING_YEARS,
      </if>
      <if test="leaveDay != null" >
        LEAVE_DAY,
      </if>
    </trim>
    <trim prefix="values (" suffix=")" suffixOverrides="," >
      <if test="alpid != null" >
        #{alpid,jdbcType=INTEGER},
      </if>
      <if test="workingYears != null" >
        #{workingYears,jdbcType=INTEGER},
      </if>
      <if test="leaveDay != null" >
        #{leaveDay,jdbcType=INTEGER},
      </if>
    </trim>
  </insert>
  <update id="updateByPrimaryKeySelective" parameterType="com.xoa.model.attendance.AttendLeaveParam" >
    <!--
      WARNING - @mbggenerated
      This element is automatically generated by MyBatis Generator, do not modify.
    -->
    update attend_leave_param
    <set >
      <if test="workingYears != null" >
        WORKING_YEARS = #{workingYears,jdbcType=INTEGER},
      </if>
      <if test="leaveDay != null" >
        LEAVE_DAY = #{leaveDay,jdbcType=INTEGER},
      </if>
    </set>
    where ALPID = #{alpid,jdbcType=INTEGER}
  </update>
  <update id="updateByPrimaryKey" parameterType="com.xoa.model.attendance.AttendLeaveParam" >
    <!--
      WARNING - @mbggenerated
      This element is automatically generated by MyBatis Generator, do not modify.
    -->
    update attend_leave_param
    set WORKING_YEARS = #{workingYears,jdbcType=INTEGER},
      LEAVE_DAY = #{leaveDay,jdbcType=INTEGER}
    where ALPID = #{alpid,jdbcType=INTEGER}
  </update>

  <select id="selectAttendLeaveParam" resultMap="BaseResultMap" parameterType="com.xoa.model.attendance.AttendLeaveParam" >
    select
    <include refid="Base_Column_List" />
    from attend_leave_param
    where  1=1
    <if test="workingYears != null" >
      WORKING_YEARS = #{workingYears,jdbcType=INTEGER},
    </if>
    <if test="leaveDay != null" >
      LEAVE_DAY = #{leaveDay,jdbcType=INTEGER},
    </if>
  </select>

  <delete id="TruncateLeaveParam">
    truncate table attend_leave_param;
  </delete>
</mapper>